.gitignore
readme.md
setup.py
bloodstone_core.egg-info/PKG-INFO
bloodstone_core.egg-info/SOURCES.txt
bloodstone_core.egg-info/dependency_links.txt
bloodstone_core.egg-info/entry_points.txt
bloodstone_core.egg-info/requires.txt
bloodstone_core.egg-info/top_level.txt
wmpy_util/__init__.py
wmpy_util/crawl_baidu.py
wmpy_util/data_process.py
wmpy_util/decorator.py
wmpy_util/es_util.py
wmpy_util/file_util.py
wmpy_util/hash_util.py
wmpy_util/img_util.py
wmpy_util/json_util.py
wmpy_util/metrics_util.py
wmpy_util/print_util.py
wmpy_util/process_bar.py
wmpy_util/re_util.py
wmpy_util/schedule_util.py
wmpy_util/sift_util.py
wmpy_util/sys_util.py
wmpy_util/tf_util.py
wmpy_util/time_util.py
wmpy_util/wanmei_api_call.py
wmpy_util/web_utils.py