Metadata-Version: 1.0
Name: bloodstone-core
Version: 0.0.7
Summary: common util of pwrd python service
Home-page: https://x.wanmei.com
Author: zhangweiwang
Author-email: zhangweiwang@pwrd.com
License: UNKNOWN
Platform: UNKNOWN
